[
  {
    "term": "공모주",
    "definition": "공모주은(는) 투자자들이 자산을 운용하고 수익을 창출하기 위해 사용하는 대표적인 금융 수단이다. 공모주은 시장 흐름과 기업 가치 분석 등을 통해 전략적으로 접근하는 것이 중요하다."
  },
  {
    "term": "통화스왑",
    "definition": "통화스왑은(는) 서로 다른 국가 간의 통화 교환 또는 관련 거래를 의미한다. 통화스왑 거래는 환율 변동에 따른 수익 또는 손실이 발생할 수 있어 주의가 필요하다."
  },
  {
    "term": "옵션",
    "definition": "옵션은(는) 기초 자산의 가치에 따라 수익이 결정되는 고위험 고수익 금융상품이다. 옵션 투자는 높은 이해도와 시장 변동성에 대한 예측이 요구된다."
  },
  {
    "term": "담보대출",
    "definition": "담보대출은(는) 자금이 필요한 개인이나 기업이 금융기관으로부터 자금을 빌리는 방식이다. 담보대출은 상환 능력과 금리에 따라 조건이 달라지며, 신용등급에 큰 영향을 미친다."
  },
  {
    "term": "지수",
    "definition": "지수은(는) 투자자들이 자산을 운용하고 수익을 창출하기 위해 사용하는 대표적인 금융 수단이다. 지수은 시장 흐름과 기업 가치 분석 등을 통해 전략적으로 접근하는 것이 중요하다."
  },
  {
    "term": "복리",
    "definition": "복리은(는) 일정 기간 동안 자금을 은행에 맡기고 이자를 받는 저축 수단이다. 안정적인 자산 관리를 원하는 개인에게 적합하며, 금리와 만기 조건을 비교해 선택해야 한다."
  },
  {
    "term": "보증",
    "definition": "보증은(는) 자금이 필요한 개인이나 기업이 금융기관으로부터 자금을 빌리는 방식이다. 보증은 상환 능력과 금리에 따라 조건이 달라지며, 신용등급에 큰 영향을 미친다."
  },
  {
    "term": "스왑",
    "definition": "스왑은(는) 기초 자산의 가치에 따라 수익이 결정되는 고위험 고수익 금융상품이다. 스왑 투자는 높은 이해도와 시장 변동성에 대한 예측이 요구된다."
  },
  {
    "term": "외화예금",
    "definition": "외화예금은(는) 서로 다른 국가 간의 통화 교환 또는 관련 거래를 의미한다. 외화예금 거래는 환율 변동에 따른 수익 또는 손실이 발생할 수 있어 주의가 필요하다."
  },
  {
    "term": "은퇴계획",
    "definition": "은퇴계획은(는) 재무 목표 달성을 위해 자산을 효율적으로 분배하고 운용하는 활동이다. 장기적인 은퇴계획 설계는 노후 대비와 위험 분산에 핵심적인 역할을 한다."
  },
  {
    "term": "선물",
    "definition": "선물은(는) 기초 자산의 가치에 따라 수익이 결정되는 고위험 고수익 금융상품이다. 선물 투자는 높은 이해도와 시장 변동성에 대한 예측이 요구된다."
  },
  {
    "term": "과세표준",
    "definition": "과세표준은(는) 국가나 지자체가 국민의 소득이나 소비에 부과하는 금전적 의무이다. 올바른 과세표준 처리를 위해 세법 지식과 정확한 회계 기준 준수가 필수적이다."
  },
  {
    "term": "자동이체",
    "definition": "자동이체은(는) 일정 기간 동안 자금을 은행에 맡기고 이자를 받는 저축 수단이다. 안정적인 자산 관리를 원하는 개인에게 적합하며, 금리와 만기 조건을 비교해 선택해야 한다."
  },
  {
    "term": "연체",
    "definition": "연체은(는) 자금이 필요한 개인이나 기업이 금융기관으로부터 자금을 빌리는 방식이다. 연체은 상환 능력과 금리에 따라 조건이 달라지며, 신용등급에 큰 영향을 미친다."
  },
  {
    "term": "매매",
    "definition": "매매은(는) 투자자들이 자산을 운용하고 수익을 창출하기 위해 사용하는 대표적인 금융 수단이다. 매매은 시장 흐름과 기업 가치 분석 등을 통해 전략적으로 접근하는 것이 중요하다."
  },
  {
    "term": "정기예금",
    "definition": "정기예금은(는) 일정 기간 동안 자금을 은행에 맡기고 이자를 받는 저축 수단이다. 안정적인 자산 관리를 원하는 개인에게 적합하며, 금리와 만기 조건을 비교해 선택해야 한다."
  },
  {
    "term": "옵션",
    "definition": "옵션은(는) 기초 자산의 가치에 따라 수익이 결정되는 고위험 고수익 금융상품이다. 옵션 투자는 높은 이해도와 시장 변동성에 대한 예측이 요구된다."
  },
  {
    "term": "연금",
    "definition": "연금은(는) 재무 목표 달성을 위해 자산을 효율적으로 분배하고 운용하는 활동이다. 장기적인 연금 설계는 노후 대비와 위험 분산에 핵심적인 역할을 한다."
  },
  {
    "term": "모바일뱅킹",
    "definition": "모바일뱅킹은(는) 정보기술을 기반으로 한 새로운 형태의 금융 서비스로, 빠른 거래와 편의성을 제공한다. 모바일뱅킹의 확산은 금융 접근성과 소비자 중심 서비스를 크게 향상시키고 있다."
  },
  {
    "term": "매매",
    "definition": "매매은(는) 투자자들이 자산을 운용하고 수익을 창출하기 위해 사용하는 대표적인 금융 수단이다. 매매은 시장 흐름과 기업 가치 분석 등을 통해 전략적으로 접근하는 것이 중요하다."
  },
  {
    "term": "신용대출",
    "definition": "신용대출은(는) 자금이 필요한 개인이나 기업이 금융기관으로부터 자금을 빌리는 방식이다. 신용대출은 상환 능력과 금리에 따라 조건이 달라지며, 신용등급에 큰 영향을 미친다."
  },
  {
    "term": "자유적금",
    "definition": "자유적금은(는) 일정 기간 동안 자금을 은행에 맡기고 이자를 받는 저축 수단이다. 안정적인 자산 관리를 원하는 개인에게 적합하며, 금리와 만기 조건을 비교해 선택해야 한다."
  },
  {
    "term": "외환시장",
    "definition": "외환시장은(는) 서로 다른 국가 간의 통화 교환 또는 관련 거래를 의미한다. 외환시장 거래는 환율 변동에 따른 수익 또는 손실이 발생할 수 있어 주의가 필요하다."
  },
  {
    "term": "AI투자",
    "definition": "AI투자은(는) 정보기술을 기반으로 한 새로운 형태의 금융 서비스로, 빠른 거래와 편의성을 제공한다. AI투자의 확산은 금융 접근성과 소비자 중심 서비스를 크게 향상시키고 있다."
  },
  {
    "term": "오픈뱅킹",
    "definition": "오픈뱅킹은(는) 정보기술을 기반으로 한 새로운 형태의 금융 서비스로, 빠른 거래와 편의성을 제공한다. 오픈뱅킹의 확산은 금융 접근성과 소비자 중심 서비스를 크게 향상시키고 있다."
  },
  {
    "term": "달러",
    "definition": "달러은(는) 서로 다른 국가 간의 통화 교환 또는 관련 거래를 의미한다. 달러 거래는 환율 변동에 따른 수익 또는 손실이 발생할 수 있어 주의가 필요하다."
  },
  {
    "term": "파생계약",
    "definition": "파생계약은(는) 기초 자산의 가치에 따라 수익이 결정되는 고위험 고수익 금융상품이다. 파생계약 투자는 높은 이해도와 시장 변동성에 대한 예측이 요구된다."
  },
  {
    "term": "콜옵션",
    "definition": "콜옵션은(는) 기초 자산의 가치에 따라 수익이 결정되는 고위험 고수익 금융상품이다. 콜옵션 투자는 높은 이해도와 시장 변동성에 대한 예측이 요구된다."
  },
  {
    "term": "통화스왑",
    "definition": "통화스왑은(는) 서로 다른 국가 간의 통화 교환 또는 관련 거래를 의미한다. 통화스왑 거래는 환율 변동에 따른 수익 또는 손실이 발생할 수 있어 주의가 필요하다."
  },
  {
    "term": "통화스왑",
    "definition": "통화스왑은(는) 서로 다른 국가 간의 통화 교환 또는 관련 거래를 의미한다. 통화스왑 거래는 환율 변동에 따른 수익 또는 손실이 발생할 수 있어 주의가 필요하다."
  },
  {
    "term": "위험관리",
    "definition": "위험관리은(는) 재무 목표 달성을 위해 자산을 효율적으로 분배하고 운용하는 활동이다. 장기적인 위험관리 설계는 노후 대비와 위험 분산에 핵심적인 역할을 한다."
  },
  {
    "term": "이자율",
    "definition": "이자율은(는) 일정 기간 동안 자금을 은행에 맡기고 이자를 받는 저축 수단이다. 안정적인 자산 관리를 원하는 개인에게 적합하며, 금리와 만기 조건을 비교해 선택해야 한다."
  },
  {
    "term": "블록체인",
    "definition": "블록체인은(는) 정보기술을 기반으로 한 새로운 형태의 금융 서비스로, 빠른 거래와 편의성을 제공한다. 블록체인의 확산은 금융 접근성과 소비자 중심 서비스를 크게 향상시키고 있다."
  },
  {
    "term": "펀드",
    "definition": "펀드은(는) 투자자들이 자산을 운용하고 수익을 창출하기 위해 사용하는 대표적인 금융 수단이다. 펀드은 시장 흐름과 기업 가치 분석 등을 통해 전략적으로 접근하는 것이 중요하다."
  },
  {
    "term": "DTI",
    "definition": "DTI은(는) 자금이 필요한 개인이나 기업이 금융기관으로부터 자금을 빌리는 방식이다. DTI은 상환 능력과 금리에 따라 조건이 달라지며, 신용등급에 큰 영향을 미친다."
  },
  {
    "term": "채권",
    "definition": "채권은(는) 투자자들이 자산을 운용하고 수익을 창출하기 위해 사용하는 대표적인 금융 수단이다. 채권은 시장 흐름과 기업 가치 분석 등을 통해 전략적으로 접근하는 것이 중요하다."
  },
  {
    "term": "단리",
    "definition": "단리은(는) 일정 기간 동안 자금을 은행에 맡기고 이자를 받는 저축 수단이다. 안정적인 자산 관리를 원하는 개인에게 적합하며, 금리와 만기 조건을 비교해 선택해야 한다."
  },
  {
    "term": "콜옵션",
    "definition": "콜옵션은(는) 기초 자산의 가치에 따라 수익이 결정되는 고위험 고수익 금융상품이다. 콜옵션 투자는 높은 이해도와 시장 변동성에 대한 예측이 요구된다."
  },
  {
    "term": "복리",
    "definition": "복리은(는) 일정 기간 동안 자금을 은행에 맡기고 이자를 받는 저축 수단이다. 안정적인 자산 관리를 원하는 개인에게 적합하며, 금리와 만기 조건을 비교해 선택해야 한다."
  },
  {
    "term": "모바일뱅킹",
    "definition": "모바일뱅킹은(는) 정보기술을 기반으로 한 새로운 형태의 금융 서비스로, 빠른 거래와 편의성을 제공한다. 모바일뱅킹의 확산은 금융 접근성과 소비자 중심 서비스를 크게 향상시키고 있다."
  },
  {
    "term": "콜옵션",
    "definition": "콜옵션은(는) 기초 자산의 가치에 따라 수익이 결정되는 고위험 고수익 금융상품이다. 콜옵션 투자는 높은 이해도와 시장 변동성에 대한 예측이 요구된다."
  },
  {
    "term": "환전수수료",
    "definition": "환전수수료은(는) 서로 다른 국가 간의 통화 교환 또는 관련 거래를 의미한다. 환전수수료 거래는 환율 변동에 따른 수익 또는 손실이 발생할 수 있어 주의가 필요하다."
  },
  {
    "term": "마이너스통장",
    "definition": "마이너스통장은(는) 자금이 필요한 개인이나 기업이 금융기관으로부터 자금을 빌리는 방식이다. 마이너스통장은 상환 능력과 금리에 따라 조건이 달라지며, 신용등급에 큰 영향을 미친다."
  },
  {
    "term": "연체이자",
    "definition": "연체이자은(는) 자금이 필요한 개인이나 기업이 금융기관으로부터 자금을 빌리는 방식이다. 연체이자은 상환 능력과 금리에 따라 조건이 달라지며, 신용등급에 큰 영향을 미친다."
  },
  {
    "term": "암호화폐",
    "definition": "암호화폐은(는) 정보기술을 기반으로 한 새로운 형태의 금융 서비스로, 빠른 거래와 편의성을 제공한다. 암호화폐의 확산은 금융 접근성과 소비자 중심 서비스를 크게 향상시키고 있다."
  },
  {
    "term": "연금",
    "definition": "연금은(는) 재무 목표 달성을 위해 자산을 효율적으로 분배하고 운용하는 활동이다. 장기적인 연금 설계는 노후 대비와 위험 분산에 핵심적인 역할을 한다."
  },
  {
    "term": "스왑",
    "definition": "스왑은(는) 기초 자산의 가치에 따라 수익이 결정되는 고위험 고수익 금융상품이다. 스왑 투자는 높은 이해도와 시장 변동성에 대한 예측이 요구된다."
  },
  {
    "term": "단리",
    "definition": "단리은(는) 일정 기간 동안 자금을 은행에 맡기고 이자를 받는 저축 수단이다. 안정적인 자산 관리를 원하는 개인에게 적합하며, 금리와 만기 조건을 비교해 선택해야 한다."
  },
  {
    "term": "블록체인",
    "definition": "블록체인은(는) 정보기술을 기반으로 한 새로운 형태의 금융 서비스로, 빠른 거래와 편의성을 제공한다. 블록체인의 확산은 금융 접근성과 소비자 중심 서비스를 크게 향상시키고 있다."
  },
  {
    "term": "환전수수료",
    "definition": "환전수수료은(는) 서로 다른 국가 간의 통화 교환 또는 관련 거래를 의미한다. 환전수수료 거래는 환율 변동에 따른 수익 또는 손실이 발생할 수 있어 주의가 필요하다."
  },
  {
    "term": "IRP",
    "definition": "IRP은(는) 재무 목표 달성을 위해 자산을 효율적으로 분배하고 운용하는 활동이다. 장기적인 IRP 설계는 노후 대비와 위험 분산에 핵심적인 역할을 한다."
  },
  {
    "term": "공제항목",
    "definition": "공제항목은(는) 국가나 지자체가 국민의 소득이나 소비에 부과하는 금전적 의무이다. 올바른 공제항목 처리를 위해 세법 지식과 정확한 회계 기준 준수가 필수적이다."
  },
  {
    "term": "레버리지",
    "definition": "레버리지은(는) 기초 자산의 가치에 따라 수익이 결정되는 고위험 고수익 금융상품이다. 레버리지 투자는 높은 이해도와 시장 변동성에 대한 예측이 요구된다."
  },
  {
    "term": "모바일뱅킹",
    "definition": "모바일뱅킹은(는) 정보기술을 기반으로 한 새로운 형태의 금융 서비스로, 빠른 거래와 편의성을 제공한다. 모바일뱅킹의 확산은 금융 접근성과 소비자 중심 서비스를 크게 향상시키고 있다."
  },
  {
    "term": "환헤지",
    "definition": "환헤지은(는) 서로 다른 국가 간의 통화 교환 또는 관련 거래를 의미한다. 환헤지 거래는 환율 변동에 따른 수익 또는 손실이 발생할 수 있어 주의가 필요하다."
  },
  {
    "term": "자산배분",
    "definition": "자산배분은(는) 재무 목표 달성을 위해 자산을 효율적으로 분배하고 운용하는 활동이다. 장기적인 자산배분 설계는 노후 대비와 위험 분산에 핵심적인 역할을 한다."
  },
  {
    "term": "우선주",
    "definition": "우선주은(는) 투자자들이 자산을 운용하고 수익을 창출하기 위해 사용하는 대표적인 금융 수단이다. 우선주은 시장 흐름과 기업 가치 분석 등을 통해 전략적으로 접근하는 것이 중요하다."
  },
  {
    "term": "오픈뱅킹",
    "definition": "오픈뱅킹은(는) 정보기술을 기반으로 한 새로운 형태의 금융 서비스로, 빠른 거래와 편의성을 제공한다. 오픈뱅킹의 확산은 금융 접근성과 소비자 중심 서비스를 크게 향상시키고 있다."
  },
  {
    "term": "옵션",
    "definition": "옵션은(는) 기초 자산의 가치에 따라 수익이 결정되는 고위험 고수익 금융상품이다. 옵션 투자는 높은 이해도와 시장 변동성에 대한 예측이 요구된다."
  },
  {
    "term": "배당",
    "definition": "배당은(는) 투자자들이 자산을 운용하고 수익을 창출하기 위해 사용하는 대표적인 금융 수단이다. 배당은 시장 흐름과 기업 가치 분석 등을 통해 전략적으로 접근하는 것이 중요하다."
  },
  {
    "term": "연체이자",
    "definition": "연체이자은(는) 자금이 필요한 개인이나 기업이 금융기관으로부터 자금을 빌리는 방식이다. 연체이자은 상환 능력과 금리에 따라 조건이 달라지며, 신용등급에 큰 영향을 미친다."
  },
  {
    "term": "디지털지갑",
    "definition": "디지털지갑은(는) 정보기술을 기반으로 한 새로운 형태의 금융 서비스로, 빠른 거래와 편의성을 제공한다. 디지털지갑의 확산은 금융 접근성과 소비자 중심 서비스를 크게 향상시키고 있다."
  },
  {
    "term": "예금자보호",
    "definition": "예금자보호은(는) 일정 기간 동안 자금을 은행에 맡기고 이자를 받는 저축 수단이다. 안정적인 자산 관리를 원하는 개인에게 적합하며, 금리와 만기 조건을 비교해 선택해야 한다."
  },
  {
    "term": "납세자",
    "definition": "납세자은(는) 국가나 지자체가 국민의 소득이나 소비에 부과하는 금전적 의무이다. 올바른 납세자 처리를 위해 세법 지식과 정확한 회계 기준 준수가 필수적이다."
  },
  {
    "term": "세액공제",
    "definition": "세액공제은(는) 국가나 지자체가 국민의 소득이나 소비에 부과하는 금전적 의무이다. 올바른 세액공제 처리를 위해 세법 지식과 정확한 회계 기준 준수가 필수적이다."
  },
  {
    "term": "모바일뱅킹",
    "definition": "모바일뱅킹은(는) 정보기술을 기반으로 한 새로운 형태의 금융 서비스로, 빠른 거래와 편의성을 제공한다. 모바일뱅킹의 확산은 금융 접근성과 소비자 중심 서비스를 크게 향상시키고 있다."
  },
  {
    "term": "유로화",
    "definition": "유로화은(는) 서로 다른 국가 간의 통화 교환 또는 관련 거래를 의미한다. 유로화 거래는 환율 변동에 따른 수익 또는 손실이 발생할 수 있어 주의가 필요하다."
  },
  {
    "term": "오픈뱅킹",
    "definition": "오픈뱅킹은(는) 정보기술을 기반으로 한 새로운 형태의 금융 서비스로, 빠른 거래와 편의성을 제공한다. 오픈뱅킹의 확산은 금융 접근성과 소비자 중심 서비스를 크게 향상시키고 있다."
  },
  {
    "term": "시가총액",
    "definition": "시가총액은(는) 투자자들이 자산을 운용하고 수익을 창출하기 위해 사용하는 대표적인 금융 수단이다. 시가총액은 시장 흐름과 기업 가치 분석 등을 통해 전략적으로 접근하는 것이 중요하다."
  },
  {
    "term": "통화스왑",
    "definition": "통화스왑은(는) 서로 다른 국가 간의 통화 교환 또는 관련 거래를 의미한다. 통화스왑 거래는 환율 변동에 따른 수익 또는 손실이 발생할 수 있어 주의가 필요하다."
  },
  {
    "term": "신용등급",
    "definition": "신용등급은(는) 자금이 필요한 개인이나 기업이 금융기관으로부터 자금을 빌리는 방식이다. 신용등급은 상환 능력과 금리에 따라 조건이 달라지며, 신용등급에 큰 영향을 미친다."
  },
  {
    "term": "생활비",
    "definition": "생활비은(는) 재무 목표 달성을 위해 자산을 효율적으로 분배하고 운용하는 활동이다. 장기적인 생활비 설계는 노후 대비와 위험 분산에 핵심적인 역할을 한다."
  },
  {
    "term": "ETF",
    "definition": "ETF은(는) 투자자들이 자산을 운용하고 수익을 창출하기 위해 사용하는 대표적인 금융 수단이다. ETF은 시장 흐름과 기업 가치 분석 등을 통해 전략적으로 접근하는 것이 중요하다."
  },
  {
    "term": "선물",
    "definition": "선물은(는) 기초 자산의 가치에 따라 수익이 결정되는 고위험 고수익 금융상품이다. 선물 투자는 높은 이해도와 시장 변동성에 대한 예측이 요구된다."
  },
  {
    "term": "달러",
    "definition": "달러은(는) 서로 다른 국가 간의 통화 교환 또는 관련 거래를 의미한다. 달러 거래는 환율 변동에 따른 수익 또는 손실이 발생할 수 있어 주의가 필요하다."
  },
  {
    "term": "연금",
    "definition": "연금은(는) 재무 목표 달성을 위해 자산을 효율적으로 분배하고 운용하는 활동이다. 장기적인 연금 설계는 노후 대비와 위험 분산에 핵심적인 역할을 한다."
  },
  {
    "term": "회계감사",
    "definition": "회계감사은(는) 국가나 지자체가 국민의 소득이나 소비에 부과하는 금전적 의무이다. 올바른 회계감사 처리를 위해 세법 지식과 정확한 회계 기준 준수가 필수적이다."
  },
  {
    "term": "레버리지",
    "definition": "레버리지은(는) 기초 자산의 가치에 따라 수익이 결정되는 고위험 고수익 금융상품이다. 레버리지 투자는 높은 이해도와 시장 변동성에 대한 예측이 요구된다."
  },
  {
    "term": "연체",
    "definition": "연체은(는) 자금이 필요한 개인이나 기업이 금융기관으로부터 자금을 빌리는 방식이다. 연체은 상환 능력과 금리에 따라 조건이 달라지며, 신용등급에 큰 영향을 미친다."
  },
  {
    "term": "채권",
    "definition": "채권은(는) 투자자들이 자산을 운용하고 수익을 창출하기 위해 사용하는 대표적인 금융 수단이다. 채권은 시장 흐름과 기업 가치 분석 등을 통해 전략적으로 접근하는 것이 중요하다."
  },
  {
    "term": "회계감사",
    "definition": "회계감사은(는) 국가나 지자체가 국민의 소득이나 소비에 부과하는 금전적 의무이다. 올바른 회계감사 처리를 위해 세법 지식과 정확한 회계 기준 준수가 필수적이다."
  },
  {
    "term": "환헤지",
    "definition": "환헤지은(는) 서로 다른 국가 간의 통화 교환 또는 관련 거래를 의미한다. 환헤지 거래는 환율 변동에 따른 수익 또는 손실이 발생할 수 있어 주의가 필요하다."
  },
  {
    "term": "환차익",
    "definition": "환차익은(는) 서로 다른 국가 간의 통화 교환 또는 관련 거래를 의미한다. 환차익 거래는 환율 변동에 따른 수익 또는 손실이 발생할 수 있어 주의가 필요하다."
  },
  {
    "term": "환차손",
    "definition": "환차손은(는) 서로 다른 국가 간의 통화 교환 또는 관련 거래를 의미한다. 환차손 거래는 환율 변동에 따른 수익 또는 손실이 발생할 수 있어 주의가 필요하다."
  },
  {
    "term": "세무조사",
    "definition": "세무조사은(는) 국가나 지자체가 국민의 소득이나 소비에 부과하는 금전적 의무이다. 올바른 세무조사 처리를 위해 세법 지식과 정확한 회계 기준 준수가 필수적이다."
  },
  {
    "term": "소득세",
    "definition": "소득세은(는) 국가나 지자체가 국민의 소득이나 소비에 부과하는 금전적 의무이다. 올바른 소득세 처리를 위해 세법 지식과 정확한 회계 기준 준수가 필수적이다."
  },
  {
    "term": "스왑",
    "definition": "스왑은(는) 기초 자산의 가치에 따라 수익이 결정되는 고위험 고수익 금융상품이다. 스왑 투자는 높은 이해도와 시장 변동성에 대한 예측이 요구된다."
  },
  {
    "term": "모바일뱅킹",
    "definition": "모바일뱅킹은(는) 정보기술을 기반으로 한 새로운 형태의 금융 서비스로, 빠른 거래와 편의성을 제공한다. 모바일뱅킹의 확산은 금융 접근성과 소비자 중심 서비스를 크게 향상시키고 있다."
  },
  {
    "term": "납세자",
    "definition": "납세자은(는) 국가나 지자체가 국민의 소득이나 소비에 부과하는 금전적 의무이다. 올바른 납세자 처리를 위해 세법 지식과 정확한 회계 기준 준수가 필수적이다."
  },
  {
    "term": "배당",
    "definition": "배당은(는) 투자자들이 자산을 운용하고 수익을 창출하기 위해 사용하는 대표적인 금융 수단이다. 배당은 시장 흐름과 기업 가치 분석 등을 통해 전략적으로 접근하는 것이 중요하다."
  },
  {
    "term": "달러",
    "definition": "달러은(는) 서로 다른 국가 간의 통화 교환 또는 관련 거래를 의미한다. 달러 거래는 환율 변동에 따른 수익 또는 손실이 발생할 수 있어 주의가 필요하다."
  },
  {
    "term": "우선주",
    "definition": "우선주은(는) 투자자들이 자산을 운용하고 수익을 창출하기 위해 사용하는 대표적인 금융 수단이다. 우선주은 시장 흐름과 기업 가치 분석 등을 통해 전략적으로 접근하는 것이 중요하다."
  },
  {
    "term": "주식",
    "definition": "주식은(는) 투자자들이 자산을 운용하고 수익을 창출하기 위해 사용하는 대표적인 금융 수단이다. 주식은 시장 흐름과 기업 가치 분석 등을 통해 전략적으로 접근하는 것이 중요하다."
  },
  {
    "term": "자산배분",
    "definition": "자산배분은(는) 재무 목표 달성을 위해 자산을 효율적으로 분배하고 운용하는 활동이다. 장기적인 자산배분 설계는 노후 대비와 위험 분산에 핵심적인 역할을 한다."
  },
  {
    "term": "매매",
    "definition": "매매은(는) 투자자들이 자산을 운용하고 수익을 창출하기 위해 사용하는 대표적인 금융 수단이다. 매매은 시장 흐름과 기업 가치 분석 등을 통해 전략적으로 접근하는 것이 중요하다."
  },
  {
    "term": "환헤지",
    "definition": "환헤지은(는) 서로 다른 국가 간의 통화 교환 또는 관련 거래를 의미한다. 환헤지 거래는 환율 변동에 따른 수익 또는 손실이 발생할 수 있어 주의가 필요하다."
  },
  {
    "term": "환차익",
    "definition": "환차익은(는) 서로 다른 국가 간의 통화 교환 또는 관련 거래를 의미한다. 환차익 거래는 환율 변동에 따른 수익 또는 손실이 발생할 수 있어 주의가 필요하다."
  },
  {
    "term": "달러",
    "definition": "달러은(는) 서로 다른 국가 간의 통화 교환 또는 관련 거래를 의미한다. 달러 거래는 환율 변동에 따른 수익 또는 손실이 발생할 수 있어 주의가 필요하다."
  },
  {
    "term": "예금자보호",
    "definition": "예금자보호은(는) 일정 기간 동안 자금을 은행에 맡기고 이자를 받는 저축 수단이다. 안정적인 자산 관리를 원하는 개인에게 적합하며, 금리와 만기 조건을 비교해 선택해야 한다."
  },
  {
    "term": "암호화폐",
    "definition": "암호화폐은(는) 정보기술을 기반으로 한 새로운 형태의 금융 서비스로, 빠른 거래와 편의성을 제공한다. 암호화폐의 확산은 금융 접근성과 소비자 중심 서비스를 크게 향상시키고 있다."
  },
  {
    "term": "풋옵션",
    "definition": "풋옵션은(는) 기초 자산의 가치에 따라 수익이 결정되는 고위험 고수익 금융상품이다. 풋옵션 투자는 높은 이해도와 시장 변동성에 대한 예측이 요구된다."
  },
  {
    "term": "통화스왑",
    "definition": "통화스왑은(는) 서로 다른 국가 간의 통화 교환 또는 관련 거래를 의미한다. 통화스왑 거래는 환율 변동에 따른 수익 또는 손실이 발생할 수 있어 주의가 필요하다."
  },
  {
    "term": "파생계약",
    "definition": "파생계약은(는) 기초 자산의 가치에 따라 수익이 결정되는 고위험 고수익 금융상품이다. 파생계약 투자는 높은 이해도와 시장 변동성에 대한 예측이 요구된다."
  },
  {
    "term": "DTI",
    "definition": "DTI은(는) 자금이 필요한 개인이나 기업이 금융기관으로부터 자금을 빌리는 방식이다. DTI은 상환 능력과 금리에 따라 조건이 달라지며, 신용등급에 큰 영향을 미친다."
  },
  {
    "term": "원리금",
    "definition": "원리금은(는) 일정 기간 동안 자금을 은행에 맡기고 이자를 받는 저축 수단이다. 안정적인 자산 관리를 원하는 개인에게 적합하며, 금리와 만기 조건을 비교해 선택해야 한다."
  },
  {
    "term": "부가가치세",
    "definition": "부가가치세은(는) 국가나 지자체가 국민의 소득이나 소비에 부과하는 금전적 의무이다. 올바른 부가가치세 처리를 위해 세법 지식과 정확한 회계 기준 준수가 필수적이다."
  },
  {
    "term": "스왑",
    "definition": "스왑은(는) 기초 자산의 가치에 따라 수익이 결정되는 고위험 고수익 금융상품이다. 스왑 투자는 높은 이해도와 시장 변동성에 대한 예측이 요구된다."
  },
  {
    "term": "연체이자",
    "definition": "연체이자은(는) 자금이 필요한 개인이나 기업이 금융기관으로부터 자금을 빌리는 방식이다. 연체이자은 상환 능력과 금리에 따라 조건이 달라지며, 신용등급에 큰 영향을 미친다."
  },
  {
    "term": "생활비",
    "definition": "생활비은(는) 재무 목표 달성을 위해 자산을 효율적으로 분배하고 운용하는 활동이다. 장기적인 생활비 설계는 노후 대비와 위험 분산에 핵심적인 역할을 한다."
  },
  {
    "term": "환전수수료",
    "definition": "환전수수료은(는) 서로 다른 국가 간의 통화 교환 또는 관련 거래를 의미한다. 환전수수료 거래는 환율 변동에 따른 수익 또는 손실이 발생할 수 있어 주의가 필요하다."
  },
  {
    "term": "ETF",
    "definition": "ETF은(는) 투자자들이 자산을 운용하고 수익을 창출하기 위해 사용하는 대표적인 금융 수단이다. ETF은 시장 흐름과 기업 가치 분석 등을 통해 전략적으로 접근하는 것이 중요하다."
  },
  {
    "term": "생활비",
    "definition": "생활비은(는) 재무 목표 달성을 위해 자산을 효율적으로 분배하고 운용하는 활동이다. 장기적인 생활비 설계는 노후 대비와 위험 분산에 핵심적인 역할을 한다."
  },
  {
    "term": "자유적금",
    "definition": "자유적금은(는) 일정 기간 동안 자금을 은행에 맡기고 이자를 받는 저축 수단이다. 안정적인 자산 관리를 원하는 개인에게 적합하며, 금리와 만기 조건을 비교해 선택해야 한다."
  },
  {
    "term": "재무설계",
    "definition": "재무설계은(는) 재무 목표 달성을 위해 자산을 효율적으로 분배하고 운용하는 활동이다. 장기적인 재무설계 설계는 노후 대비와 위험 분산에 핵심적인 역할을 한다."
  },
  {
    "term": "ETF",
    "definition": "ETF은(는) 투자자들이 자산을 운용하고 수익을 창출하기 위해 사용하는 대표적인 금융 수단이다. ETF은 시장 흐름과 기업 가치 분석 등을 통해 전략적으로 접근하는 것이 중요하다."
  },
  {
    "term": "레버리지",
    "definition": "레버리지은(는) 기초 자산의 가치에 따라 수익이 결정되는 고위험 고수익 금융상품이다. 레버리지 투자는 높은 이해도와 시장 변동성에 대한 예측이 요구된다."
  },
  {
    "term": "위험관리",
    "definition": "위험관리은(는) 재무 목표 달성을 위해 자산을 효율적으로 분배하고 운용하는 활동이다. 장기적인 위험관리 설계는 노후 대비와 위험 분산에 핵심적인 역할을 한다."
  },
  {
    "term": "종합소득세",
    "definition": "종합소득세은(는) 국가나 지자체가 국민의 소득이나 소비에 부과하는 금전적 의무이다. 올바른 종합소득세 처리를 위해 세법 지식과 정확한 회계 기준 준수가 필수적이다."
  },
  {
    "term": "디지털지갑",
    "definition": "디지털지갑은(는) 정보기술을 기반으로 한 새로운 형태의 금융 서비스로, 빠른 거래와 편의성을 제공한다. 디지털지갑의 확산은 금융 접근성과 소비자 중심 서비스를 크게 향상시키고 있다."
  },
  {
    "term": "종합소득세",
    "definition": "종합소득세은(는) 국가나 지자체가 국민의 소득이나 소비에 부과하는 금전적 의무이다. 올바른 종합소득세 처리를 위해 세법 지식과 정확한 회계 기준 준수가 필수적이다."
  },
  {
    "term": "세액공제",
    "definition": "세액공제은(는) 국가나 지자체가 국민의 소득이나 소비에 부과하는 금전적 의무이다. 올바른 세액공제 처리를 위해 세법 지식과 정확한 회계 기준 준수가 필수적이다."
  },
  {
    "term": "시가총액",
    "definition": "시가총액은(는) 투자자들이 자산을 운용하고 수익을 창출하기 위해 사용하는 대표적인 금융 수단이다. 시가총액은 시장 흐름과 기업 가치 분석 등을 통해 전략적으로 접근하는 것이 중요하다."
  },
  {
    "term": "디지털지갑",
    "definition": "디지털지갑은(는) 정보기술을 기반으로 한 새로운 형태의 금융 서비스로, 빠른 거래와 편의성을 제공한다. 디지털지갑의 확산은 금융 접근성과 소비자 중심 서비스를 크게 향상시키고 있다."
  },
  {
    "term": "회계감사",
    "definition": "회계감사은(는) 국가나 지자체가 국민의 소득이나 소비에 부과하는 금전적 의무이다. 올바른 회계감사 처리를 위해 세법 지식과 정확한 회계 기준 준수가 필수적이다."
  },
  {
    "term": "기초자산",
    "definition": "기초자산은(는) 기초 자산의 가치에 따라 수익이 결정되는 고위험 고수익 금융상품이다. 기초자산 투자는 높은 이해도와 시장 변동성에 대한 예측이 요구된다."
  },
  {
    "term": "담보대출",
    "definition": "담보대출은(는) 자금이 필요한 개인이나 기업이 금융기관으로부터 자금을 빌리는 방식이다. 담보대출은 상환 능력과 금리에 따라 조건이 달라지며, 신용등급에 큰 영향을 미친다."
  },
  {
    "term": "기초자산",
    "definition": "기초자산은(는) 기초 자산의 가치에 따라 수익이 결정되는 고위험 고수익 금융상품이다. 기초자산 투자는 높은 이해도와 시장 변동성에 대한 예측이 요구된다."
  },
  {
    "term": "생활비",
    "definition": "생활비은(는) 재무 목표 달성을 위해 자산을 효율적으로 분배하고 운용하는 활동이다. 장기적인 생활비 설계는 노후 대비와 위험 분산에 핵심적인 역할을 한다."
  },
  {
    "term": "재무설계",
    "definition": "재무설계은(는) 재무 목표 달성을 위해 자산을 효율적으로 분배하고 운용하는 활동이다. 장기적인 재무설계 설계는 노후 대비와 위험 분산에 핵심적인 역할을 한다."
  },
  {
    "term": "외환시장",
    "definition": "외환시장은(는) 서로 다른 국가 간의 통화 교환 또는 관련 거래를 의미한다. 외환시장 거래는 환율 변동에 따른 수익 또는 손실이 발생할 수 있어 주의가 필요하다."
  },
  {
    "term": "보증",
    "definition": "보증은(는) 자금이 필요한 개인이나 기업이 금융기관으로부터 자금을 빌리는 방식이다. 보증은 상환 능력과 금리에 따라 조건이 달라지며, 신용등급에 큰 영향을 미친다."
  },
  {
    "term": "펀드",
    "definition": "펀드은(는) 투자자들이 자산을 운용하고 수익을 창출하기 위해 사용하는 대표적인 금융 수단이다. 펀드은 시장 흐름과 기업 가치 분석 등을 통해 전략적으로 접근하는 것이 중요하다."
  },
  {
    "term": "납세자",
    "definition": "납세자은(는) 국가나 지자체가 국민의 소득이나 소비에 부과하는 금전적 의무이다. 올바른 납세자 처리를 위해 세법 지식과 정확한 회계 기준 준수가 필수적이다."
  },
  {
    "term": "신용대출",
    "definition": "신용대출은(는) 자금이 필요한 개인이나 기업이 금융기관으로부터 자금을 빌리는 방식이다. 신용대출은 상환 능력과 금리에 따라 조건이 달라지며, 신용등급에 큰 영향을 미친다."
  },
  {
    "term": "담보대출",
    "definition": "담보대출은(는) 자금이 필요한 개인이나 기업이 금융기관으로부터 자금을 빌리는 방식이다. 담보대출은 상환 능력과 금리에 따라 조건이 달라지며, 신용등급에 큰 영향을 미친다."
  },
  {
    "term": "채권",
    "definition": "채권은(는) 투자자들이 자산을 운용하고 수익을 창출하기 위해 사용하는 대표적인 금융 수단이다. 채권은 시장 흐름과 기업 가치 분석 등을 통해 전략적으로 접근하는 것이 중요하다."
  },
  {
    "term": "주식",
    "definition": "주식은(는) 투자자들이 자산을 운용하고 수익을 창출하기 위해 사용하는 대표적인 금융 수단이다. 주식은 시장 흐름과 기업 가치 분석 등을 통해 전략적으로 접근하는 것이 중요하다."
  },
  {
    "term": "우선주",
    "definition": "우선주은(는) 투자자들이 자산을 운용하고 수익을 창출하기 위해 사용하는 대표적인 금융 수단이다. 우선주은 시장 흐름과 기업 가치 분석 등을 통해 전략적으로 접근하는 것이 중요하다."
  },
  {
    "term": "채권",
    "definition": "채권은(는) 투자자들이 자산을 운용하고 수익을 창출하기 위해 사용하는 대표적인 금융 수단이다. 채권은 시장 흐름과 기업 가치 분석 등을 통해 전략적으로 접근하는 것이 중요하다."
  },
  {
    "term": "AI투자",
    "definition": "AI투자은(는) 정보기술을 기반으로 한 새로운 형태의 금융 서비스로, 빠른 거래와 편의성을 제공한다. AI투자의 확산은 금융 접근성과 소비자 중심 서비스를 크게 향상시키고 있다."
  },
  {
    "term": "현금흐름",
    "definition": "현금흐름은(는) 재무 목표 달성을 위해 자산을 효율적으로 분배하고 운용하는 활동이다. 장기적인 현금흐름 설계는 노후 대비와 위험 분산에 핵심적인 역할을 한다."
  },
  {
    "term": "정기예금",
    "definition": "정기예금은(는) 일정 기간 동안 자금을 은행에 맡기고 이자를 받는 저축 수단이다. 안정적인 자산 관리를 원하는 개인에게 적합하며, 금리와 만기 조건을 비교해 선택해야 한다."
  },
  {
    "term": "기초자산",
    "definition": "기초자산은(는) 기초 자산의 가치에 따라 수익이 결정되는 고위험 고수익 금융상품이다. 기초자산 투자는 높은 이해도와 시장 변동성에 대한 예측이 요구된다."
  },
  {
    "term": "비대면계좌",
    "definition": "비대면계좌은(는) 정보기술을 기반으로 한 새로운 형태의 금융 서비스로, 빠른 거래와 편의성을 제공한다. 비대면계좌의 확산은 금융 접근성과 소비자 중심 서비스를 크게 향상시키고 있다."
  },
  {
    "term": "외화예금",
    "definition": "외화예금은(는) 서로 다른 국가 간의 통화 교환 또는 관련 거래를 의미한다. 외화예금 거래는 환율 변동에 따른 수익 또는 손실이 발생할 수 있어 주의가 필요하다."
  },
  {
    "term": "콜옵션",
    "definition": "콜옵션은(는) 기초 자산의 가치에 따라 수익이 결정되는 고위험 고수익 금융상품이다. 콜옵션 투자는 높은 이해도와 시장 변동성에 대한 예측이 요구된다."
  },
  {
    "term": "납세자",
    "definition": "납세자은(는) 국가나 지자체가 국민의 소득이나 소비에 부과하는 금전적 의무이다. 올바른 납세자 처리를 위해 세법 지식과 정확한 회계 기준 준수가 필수적이다."
  },
  {
    "term": "예금자보호",
    "definition": "예금자보호은(는) 일정 기간 동안 자금을 은행에 맡기고 이자를 받는 저축 수단이다. 안정적인 자산 관리를 원하는 개인에게 적합하며, 금리와 만기 조건을 비교해 선택해야 한다."
  },
  {
    "term": "회계감사",
    "definition": "회계감사은(는) 국가나 지자체가 국민의 소득이나 소비에 부과하는 금전적 의무이다. 올바른 회계감사 처리를 위해 세법 지식과 정확한 회계 기준 준수가 필수적이다."
  },
  {
    "term": "공모주",
    "definition": "공모주은(는) 투자자들이 자산을 운용하고 수익을 창출하기 위해 사용하는 대표적인 금융 수단이다. 공모주은 시장 흐름과 기업 가치 분석 등을 통해 전략적으로 접근하는 것이 중요하다."
  },
  {
    "term": "예금자보호",
    "definition": "예금자보호은(는) 일정 기간 동안 자금을 은행에 맡기고 이자를 받는 저축 수단이다. 안정적인 자산 관리를 원하는 개인에게 적합하며, 금리와 만기 조건을 비교해 선택해야 한다."
  },
  {
    "term": "채권",
    "definition": "채권은(는) 투자자들이 자산을 운용하고 수익을 창출하기 위해 사용하는 대표적인 금융 수단이다. 채권은 시장 흐름과 기업 가치 분석 등을 통해 전략적으로 접근하는 것이 중요하다."
  },
  {
    "term": "복리",
    "definition": "복리은(는) 일정 기간 동안 자금을 은행에 맡기고 이자를 받는 저축 수단이다. 안정적인 자산 관리를 원하는 개인에게 적합하며, 금리와 만기 조건을 비교해 선택해야 한다."
  },
  {
    "term": "기초자산",
    "definition": "기초자산은(는) 기초 자산의 가치에 따라 수익이 결정되는 고위험 고수익 금융상품이다. 기초자산 투자는 높은 이해도와 시장 변동성에 대한 예측이 요구된다."
  },
  {
    "term": "적금",
    "definition": "적금은(는) 일정 기간 동안 자금을 은행에 맡기고 이자를 받는 저축 수단이다. 안정적인 자산 관리를 원하는 개인에게 적합하며, 금리와 만기 조건을 비교해 선택해야 한다."
  },
  {
    "term": "옵션",
    "definition": "옵션은(는) 기초 자산의 가치에 따라 수익이 결정되는 고위험 고수익 금융상품이다. 옵션 투자는 높은 이해도와 시장 변동성에 대한 예측이 요구된다."
  },
  {
    "term": "부가가치세",
    "definition": "부가가치세은(는) 국가나 지자체가 국민의 소득이나 소비에 부과하는 금전적 의무이다. 올바른 부가가치세 처리를 위해 세법 지식과 정확한 회계 기준 준수가 필수적이다."
  },
  {
    "term": "회계감사",
    "definition": "회계감사은(는) 국가나 지자체가 국민의 소득이나 소비에 부과하는 금전적 의무이다. 올바른 회계감사 처리를 위해 세법 지식과 정확한 회계 기준 준수가 필수적이다."
  },
  {
    "term": "배당",
    "definition": "배당은(는) 투자자들이 자산을 운용하고 수익을 창출하기 위해 사용하는 대표적인 금융 수단이다. 배당은 시장 흐름과 기업 가치 분석 등을 통해 전략적으로 접근하는 것이 중요하다."
  },
  {
    "term": "퇴직연금",
    "definition": "퇴직연금은(는) 재무 목표 달성을 위해 자산을 효율적으로 분배하고 운용하는 활동이다. 장기적인 퇴직연금 설계는 노후 대비와 위험 분산에 핵심적인 역할을 한다."
  },
  {
    "term": "자동이체",
    "definition": "자동이체은(는) 일정 기간 동안 자금을 은행에 맡기고 이자를 받는 저축 수단이다. 안정적인 자산 관리를 원하는 개인에게 적합하며, 금리와 만기 조건을 비교해 선택해야 한다."
  },
  {
    "term": "비대면계좌",
    "definition": "비대면계좌은(는) 정보기술을 기반으로 한 새로운 형태의 금융 서비스로, 빠른 거래와 편의성을 제공한다. 비대면계좌의 확산은 금융 접근성과 소비자 중심 서비스를 크게 향상시키고 있다."
  },
  {
    "term": "환차손",
    "definition": "환차손은(는) 서로 다른 국가 간의 통화 교환 또는 관련 거래를 의미한다. 환차손 거래는 환율 변동에 따른 수익 또는 손실이 발생할 수 있어 주의가 필요하다."
  },
  {
    "term": "옵션",
    "definition": "옵션은(는) 기초 자산의 가치에 따라 수익이 결정되는 고위험 고수익 금융상품이다. 옵션 투자는 높은 이해도와 시장 변동성에 대한 예측이 요구된다."
  },
  {
    "term": "상환",
    "definition": "상환은(는) 자금이 필요한 개인이나 기업이 금융기관으로부터 자금을 빌리는 방식이다. 상환은 상환 능력과 금리에 따라 조건이 달라지며, 신용등급에 큰 영향을 미친다."
  },
  {
    "term": "연금",
    "definition": "연금은(는) 재무 목표 달성을 위해 자산을 효율적으로 분배하고 운용하는 활동이다. 장기적인 연금 설계는 노후 대비와 위험 분산에 핵심적인 역할을 한다."
  },
  {
    "term": "우선주",
    "definition": "우선주은(는) 투자자들이 자산을 운용하고 수익을 창출하기 위해 사용하는 대표적인 금융 수단이다. 우선주은 시장 흐름과 기업 가치 분석 등을 통해 전략적으로 접근하는 것이 중요하다."
  },
  {
    "term": "복리",
    "definition": "복리은(는) 일정 기간 동안 자금을 은행에 맡기고 이자를 받는 저축 수단이다. 안정적인 자산 관리를 원하는 개인에게 적합하며, 금리와 만기 조건을 비교해 선택해야 한다."
  },
  {
    "term": "풋옵션",
    "definition": "풋옵션은(는) 기초 자산의 가치에 따라 수익이 결정되는 고위험 고수익 금융상품이다. 풋옵션 투자는 높은 이해도와 시장 변동성에 대한 예측이 요구된다."
  },
  {
    "term": "오픈뱅킹",
    "definition": "오픈뱅킹은(는) 정보기술을 기반으로 한 새로운 형태의 금융 서비스로, 빠른 거래와 편의성을 제공한다. 오픈뱅킹의 확산은 금융 접근성과 소비자 중심 서비스를 크게 향상시키고 있다."
  },
  {
    "term": "스왑",
    "definition": "스왑은(는) 기초 자산의 가치에 따라 수익이 결정되는 고위험 고수익 금융상품이다. 스왑 투자는 높은 이해도와 시장 변동성에 대한 예측이 요구된다."
  },
  {
    "term": "채권",
    "definition": "채권은(는) 투자자들이 자산을 운용하고 수익을 창출하기 위해 사용하는 대표적인 금융 수단이다. 채권은 시장 흐름과 기업 가치 분석 등을 통해 전략적으로 접근하는 것이 중요하다."
  },
  {
    "term": "세무조사",
    "definition": "세무조사은(는) 국가나 지자체가 국민의 소득이나 소비에 부과하는 금전적 의무이다. 올바른 세무조사 처리를 위해 세법 지식과 정확한 회계 기준 준수가 필수적이다."
  },
  {
    "term": "신용대출",
    "definition": "신용대출은(는) 자금이 필요한 개인이나 기업이 금융기관으로부터 자금을 빌리는 방식이다. 신용대출은 상환 능력과 금리에 따라 조건이 달라지며, 신용등급에 큰 영향을 미친다."
  },
  {
    "term": "원리금",
    "definition": "원리금은(는) 일정 기간 동안 자금을 은행에 맡기고 이자를 받는 저축 수단이다. 안정적인 자산 관리를 원하는 개인에게 적합하며, 금리와 만기 조건을 비교해 선택해야 한다."
  },
  {
    "term": "원리금",
    "definition": "원리금은(는) 일정 기간 동안 자금을 은행에 맡기고 이자를 받는 저축 수단이다. 안정적인 자산 관리를 원하는 개인에게 적합하며, 금리와 만기 조건을 비교해 선택해야 한다."
  },
  {
    "term": "은퇴계획",
    "definition": "은퇴계획은(는) 재무 목표 달성을 위해 자산을 효율적으로 분배하고 운용하는 활동이다. 장기적인 은퇴계획 설계는 노후 대비와 위험 분산에 핵심적인 역할을 한다."
  },
  {
    "term": "보증",
    "definition": "보증은(는) 자금이 필요한 개인이나 기업이 금융기관으로부터 자금을 빌리는 방식이다. 보증은 상환 능력과 금리에 따라 조건이 달라지며, 신용등급에 큰 영향을 미친다."
  },
  {
    "term": "우선주",
    "definition": "우선주은(는) 투자자들이 자산을 운용하고 수익을 창출하기 위해 사용하는 대표적인 금융 수단이다. 우선주은 시장 흐름과 기업 가치 분석 등을 통해 전략적으로 접근하는 것이 중요하다."
  },
  {
    "term": "세액공제",
    "definition": "세액공제은(는) 국가나 지자체가 국민의 소득이나 소비에 부과하는 금전적 의무이다. 올바른 세액공제 처리를 위해 세법 지식과 정확한 회계 기준 준수가 필수적이다."
  },
  {
    "term": "환헤지",
    "definition": "환헤지은(는) 서로 다른 국가 간의 통화 교환 또는 관련 거래를 의미한다. 환헤지 거래는 환율 변동에 따른 수익 또는 손실이 발생할 수 있어 주의가 필요하다."
  },
  {
    "term": "자산배분",
    "definition": "자산배분은(는) 재무 목표 달성을 위해 자산을 효율적으로 분배하고 운용하는 활동이다. 장기적인 자산배분 설계는 노후 대비와 위험 분산에 핵심적인 역할을 한다."
  },
  {
    "term": "콜옵션",
    "definition": "콜옵션은(는) 기초 자산의 가치에 따라 수익이 결정되는 고위험 고수익 금융상품이다. 콜옵션 투자는 높은 이해도와 시장 변동성에 대한 예측이 요구된다."
  },
  {
    "term": "단리",
    "definition": "단리은(는) 일정 기간 동안 자금을 은행에 맡기고 이자를 받는 저축 수단이다. 안정적인 자산 관리를 원하는 개인에게 적합하며, 금리와 만기 조건을 비교해 선택해야 한다."
  },
  {
    "term": "암호화폐",
    "definition": "암호화폐은(는) 정보기술을 기반으로 한 새로운 형태의 금융 서비스로, 빠른 거래와 편의성을 제공한다. 암호화폐의 확산은 금융 접근성과 소비자 중심 서비스를 크게 향상시키고 있다."
  },
  {
    "term": "환헤지",
    "definition": "환헤지은(는) 서로 다른 국가 간의 통화 교환 또는 관련 거래를 의미한다. 환헤지 거래는 환율 변동에 따른 수익 또는 손실이 발생할 수 있어 주의가 필요하다."
  },
  {
    "term": "종합소득세",
    "definition": "종합소득세은(는) 국가나 지자체가 국민의 소득이나 소비에 부과하는 금전적 의무이다. 올바른 종합소득세 처리를 위해 세법 지식과 정확한 회계 기준 준수가 필수적이다."
  },
  {
    "term": "환차손",
    "definition": "환차손은(는) 서로 다른 국가 간의 통화 교환 또는 관련 거래를 의미한다. 환차손 거래는 환율 변동에 따른 수익 또는 손실이 발생할 수 있어 주의가 필요하다."
  },
  {
    "term": "지출관리",
    "definition": "지출관리은(는) 재무 목표 달성을 위해 자산을 효율적으로 분배하고 운용하는 활동이다. 장기적인 지출관리 설계는 노후 대비와 위험 분산에 핵심적인 역할을 한다."
  },
  {
    "term": "가상자산",
    "definition": "가상자산은(는) 정보기술을 기반으로 한 새로운 형태의 금융 서비스로, 빠른 거래와 편의성을 제공한다. 가상자산의 확산은 금융 접근성과 소비자 중심 서비스를 크게 향상시키고 있다."
  },
  {
    "term": "배당",
    "definition": "배당은(는) 투자자들이 자산을 운용하고 수익을 창출하기 위해 사용하는 대표적인 금융 수단이다. 배당은 시장 흐름과 기업 가치 분석 등을 통해 전략적으로 접근하는 것이 중요하다."
  },
  {
    "term": "재무설계",
    "definition": "재무설계은(는) 재무 목표 달성을 위해 자산을 효율적으로 분배하고 운용하는 활동이다. 장기적인 재무설계 설계는 노후 대비와 위험 분산에 핵심적인 역할을 한다."
  },
  {
    "term": "환전수수료",
    "definition": "환전수수료은(는) 서로 다른 국가 간의 통화 교환 또는 관련 거래를 의미한다. 환전수수료 거래는 환율 변동에 따른 수익 또는 손실이 발생할 수 있어 주의가 필요하다."
  },
  {
    "term": "환헤지",
    "definition": "환헤지은(는) 서로 다른 국가 간의 통화 교환 또는 관련 거래를 의미한다. 환헤지 거래는 환율 변동에 따른 수익 또는 손실이 발생할 수 있어 주의가 필요하다."
  },
  {
    "term": "연체",
    "definition": "연체은(는) 자금이 필요한 개인이나 기업이 금융기관으로부터 자금을 빌리는 방식이다. 연체은 상환 능력과 금리에 따라 조건이 달라지며, 신용등급에 큰 영향을 미친다."
  },
  {
    "term": "가상자산",
    "definition": "가상자산은(는) 정보기술을 기반으로 한 새로운 형태의 금융 서비스로, 빠른 거래와 편의성을 제공한다. 가상자산의 확산은 금융 접근성과 소비자 중심 서비스를 크게 향상시키고 있다."
  },
  {
    "term": "채권",
    "definition": "채권은(는) 투자자들이 자산을 운용하고 수익을 창출하기 위해 사용하는 대표적인 금융 수단이다. 채권은 시장 흐름과 기업 가치 분석 등을 통해 전략적으로 접근하는 것이 중요하다."
  },
  {
    "term": "예금자보호",
    "definition": "예금자보호은(는) 일정 기간 동안 자금을 은행에 맡기고 이자를 받는 저축 수단이다. 안정적인 자산 관리를 원하는 개인에게 적합하며, 금리와 만기 조건을 비교해 선택해야 한다."
  },
  {
    "term": "모바일뱅킹",
    "definition": "모바일뱅킹은(는) 정보기술을 기반으로 한 새로운 형태의 금융 서비스로, 빠른 거래와 편의성을 제공한다. 모바일뱅킹의 확산은 금융 접근성과 소비자 중심 서비스를 크게 향상시키고 있다."
  },
  {
    "term": "보증",
    "definition": "보증은(는) 자금이 필요한 개인이나 기업이 금융기관으로부터 자금을 빌리는 방식이다. 보증은 상환 능력과 금리에 따라 조건이 달라지며, 신용등급에 큰 영향을 미친다."
  },
  {
    "term": "가상자산",
    "definition": "가상자산은(는) 정보기술을 기반으로 한 새로운 형태의 금융 서비스로, 빠른 거래와 편의성을 제공한다. 가상자산의 확산은 금융 접근성과 소비자 중심 서비스를 크게 향상시키고 있다."
  },
  {
    "term": "원리금",
    "definition": "원리금은(는) 일정 기간 동안 자금을 은행에 맡기고 이자를 받는 저축 수단이다. 안정적인 자산 관리를 원하는 개인에게 적합하며, 금리와 만기 조건을 비교해 선택해야 한다."
  },
  {
    "term": "외화예금",
    "definition": "외화예금은(는) 서로 다른 국가 간의 통화 교환 또는 관련 거래를 의미한다. 외화예금 거래는 환율 변동에 따른 수익 또는 손실이 발생할 수 있어 주의가 필요하다."
  },
  {
    "term": "오픈뱅킹",
    "definition": "오픈뱅킹은(는) 정보기술을 기반으로 한 새로운 형태의 금융 서비스로, 빠른 거래와 편의성을 제공한다. 오픈뱅킹의 확산은 금융 접근성과 소비자 중심 서비스를 크게 향상시키고 있다."
  },
  {
    "term": "퇴직연금",
    "definition": "퇴직연금은(는) 재무 목표 달성을 위해 자산을 효율적으로 분배하고 운용하는 활동이다. 장기적인 퇴직연금 설계는 노후 대비와 위험 분산에 핵심적인 역할을 한다."
  },
  {
    "term": "담보대출",
    "definition": "담보대출은(는) 자금이 필요한 개인이나 기업이 금융기관으로부터 자금을 빌리는 방식이다. 담보대출은 상환 능력과 금리에 따라 조건이 달라지며, 신용등급에 큰 영향을 미친다."
  },
  {
    "term": "유로화",
    "definition": "유로화은(는) 서로 다른 국가 간의 통화 교환 또는 관련 거래를 의미한다. 유로화 거래는 환율 변동에 따른 수익 또는 손실이 발생할 수 있어 주의가 필요하다."
  },
  {
    "term": "모바일뱅킹",
    "definition": "모바일뱅킹은(는) 정보기술을 기반으로 한 새로운 형태의 금융 서비스로, 빠른 거래와 편의성을 제공한다. 모바일뱅킹의 확산은 금융 접근성과 소비자 중심 서비스를 크게 향상시키고 있다."
  },
  {
    "term": "위험관리",
    "definition": "위험관리은(는) 재무 목표 달성을 위해 자산을 효율적으로 분배하고 운용하는 활동이다. 장기적인 위험관리 설계는 노후 대비와 위험 분산에 핵심적인 역할을 한다."
  },
  {
    "term": "풋옵션",
    "definition": "풋옵션은(는) 기초 자산의 가치에 따라 수익이 결정되는 고위험 고수익 금융상품이다. 풋옵션 투자는 높은 이해도와 시장 변동성에 대한 예측이 요구된다."
  },
  {
    "term": "DTI",
    "definition": "DTI은(는) 자금이 필요한 개인이나 기업이 금융기관으로부터 자금을 빌리는 방식이다. DTI은 상환 능력과 금리에 따라 조건이 달라지며, 신용등급에 큰 영향을 미친다."
  },
  {
    "term": "연체이자",
    "definition": "연체이자은(는) 자금이 필요한 개인이나 기업이 금융기관으로부터 자금을 빌리는 방식이다. 연체이자은 상환 능력과 금리에 따라 조건이 달라지며, 신용등급에 큰 영향을 미친다."
  },
  {
    "term": "유로화",
    "definition": "유로화은(는) 서로 다른 국가 간의 통화 교환 또는 관련 거래를 의미한다. 유로화 거래는 환율 변동에 따른 수익 또는 손실이 발생할 수 있어 주의가 필요하다."
  },
  {
    "term": "간편결제",
    "definition": "간편결제은(는) 정보기술을 기반으로 한 새로운 형태의 금융 서비스로, 빠른 거래와 편의성을 제공한다. 간편결제의 확산은 금융 접근성과 소비자 중심 서비스를 크게 향상시키고 있다."
  },
  {
    "term": "보증",
    "definition": "보증은(는) 자금이 필요한 개인이나 기업이 금융기관으로부터 자금을 빌리는 방식이다. 보증은 상환 능력과 금리에 따라 조건이 달라지며, 신용등급에 큰 영향을 미친다."
  },
  {
    "term": "지출관리",
    "definition": "지출관리은(는) 재무 목표 달성을 위해 자산을 효율적으로 분배하고 운용하는 활동이다. 장기적인 지출관리 설계는 노후 대비와 위험 분산에 핵심적인 역할을 한다."
  },
  {
    "term": "복리",
    "definition": "복리은(는) 일정 기간 동안 자금을 은행에 맡기고 이자를 받는 저축 수단이다. 안정적인 자산 관리를 원하는 개인에게 적합하며, 금리와 만기 조건을 비교해 선택해야 한다."
  },
  {
    "term": "주식",
    "definition": "주식은(는) 투자자들이 자산을 운용하고 수익을 창출하기 위해 사용하는 대표적인 금융 수단이다. 주식은 시장 흐름과 기업 가치 분석 등을 통해 전략적으로 접근하는 것이 중요하다."
  },
  {
    "term": "정기예금",
    "definition": "정기예금은(는) 일정 기간 동안 자금을 은행에 맡기고 이자를 받는 저축 수단이다. 안정적인 자산 관리를 원하는 개인에게 적합하며, 금리와 만기 조건을 비교해 선택해야 한다."
  },
  {
    "term": "CFD",
    "definition": "CFD은(는) 기초 자산의 가치에 따라 수익이 결정되는 고위험 고수익 금융상품이다. CFD 투자는 높은 이해도와 시장 변동성에 대한 예측이 요구된다."
  },
  {
    "term": "환차익",
    "definition": "환차익은(는) 서로 다른 국가 간의 통화 교환 또는 관련 거래를 의미한다. 환차익 거래는 환율 변동에 따른 수익 또는 손실이 발생할 수 있어 주의가 필요하다."
  },
  {
    "term": "공제항목",
    "definition": "공제항목은(는) 국가나 지자체가 국민의 소득이나 소비에 부과하는 금전적 의무이다. 올바른 공제항목 처리를 위해 세법 지식과 정확한 회계 기준 준수가 필수적이다."
  },
  {
    "term": "세무조사",
    "definition": "세무조사은(는) 국가나 지자체가 국민의 소득이나 소비에 부과하는 금전적 의무이다. 올바른 세무조사 처리를 위해 세법 지식과 정확한 회계 기준 준수가 필수적이다."
  },
  {
    "term": "과세표준",
    "definition": "과세표준은(는) 국가나 지자체가 국민의 소득이나 소비에 부과하는 금전적 의무이다. 올바른 과세표준 처리를 위해 세법 지식과 정확한 회계 기준 준수가 필수적이다."
  },
  {
    "term": "법인세",
    "definition": "법인세은(는) 국가나 지자체가 국민의 소득이나 소비에 부과하는 금전적 의무이다. 올바른 법인세 처리를 위해 세법 지식과 정확한 회계 기준 준수가 필수적이다."
  },
  {
    "term": "기초자산",
    "definition": "기초자산은(는) 기초 자산의 가치에 따라 수익이 결정되는 고위험 고수익 금융상품이다. 기초자산 투자는 높은 이해도와 시장 변동성에 대한 예측이 요구된다."
  },
  {
    "term": "마이너스통장",
    "definition": "마이너스통장은(는) 자금이 필요한 개인이나 기업이 금융기관으로부터 자금을 빌리는 방식이다. 마이너스통장은 상환 능력과 금리에 따라 조건이 달라지며, 신용등급에 큰 영향을 미친다."
  },
  {
    "term": "공모주",
    "definition": "공모주은(는) 투자자들이 자산을 운용하고 수익을 창출하기 위해 사용하는 대표적인 금융 수단이다. 공모주은 시장 흐름과 기업 가치 분석 등을 통해 전략적으로 접근하는 것이 중요하다."
  },
  {
    "term": "IRP",
    "definition": "IRP은(는) 재무 목표 달성을 위해 자산을 효율적으로 분배하고 운용하는 활동이다. 장기적인 IRP 설계는 노후 대비와 위험 분산에 핵심적인 역할을 한다."
  },
  {
    "term": "현금흐름",
    "definition": "현금흐름은(는) 재무 목표 달성을 위해 자산을 효율적으로 분배하고 운용하는 활동이다. 장기적인 현금흐름 설계는 노후 대비와 위험 분산에 핵심적인 역할을 한다."
  },
  {
    "term": "보증",
    "definition": "보증은(는) 자금이 필요한 개인이나 기업이 금융기관으로부터 자금을 빌리는 방식이다. 보증은 상환 능력과 금리에 따라 조건이 달라지며, 신용등급에 큰 영향을 미친다."
  },
  {
    "term": "자동이체",
    "definition": "자동이체은(는) 일정 기간 동안 자금을 은행에 맡기고 이자를 받는 저축 수단이다. 안정적인 자산 관리를 원하는 개인에게 적합하며, 금리와 만기 조건을 비교해 선택해야 한다."
  },
  {
    "term": "외환시장",
    "definition": "외환시장은(는) 서로 다른 국가 간의 통화 교환 또는 관련 거래를 의미한다. 외환시장 거래는 환율 변동에 따른 수익 또는 손실이 발생할 수 있어 주의가 필요하다."
  },
  {
    "term": "자유적금",
    "definition": "자유적금은(는) 일정 기간 동안 자금을 은행에 맡기고 이자를 받는 저축 수단이다. 안정적인 자산 관리를 원하는 개인에게 적합하며, 금리와 만기 조건을 비교해 선택해야 한다."
  },
  {
    "term": "자산배분",
    "definition": "자산배분은(는) 재무 목표 달성을 위해 자산을 효율적으로 분배하고 운용하는 활동이다. 장기적인 자산배분 설계는 노후 대비와 위험 분산에 핵심적인 역할을 한다."
  },
  {
    "term": "과세표준",
    "definition": "과세표준은(는) 국가나 지자체가 국민의 소득이나 소비에 부과하는 금전적 의무이다. 올바른 과세표준 처리를 위해 세법 지식과 정확한 회계 기준 준수가 필수적이다."
  },
  {
    "term": "세액공제",
    "definition": "세액공제은(는) 국가나 지자체가 국민의 소득이나 소비에 부과하는 금전적 의무이다. 올바른 세액공제 처리를 위해 세법 지식과 정확한 회계 기준 준수가 필수적이다."
  },
  {
    "term": "유로화",
    "definition": "유로화은(는) 서로 다른 국가 간의 통화 교환 또는 관련 거래를 의미한다. 유로화 거래는 환율 변동에 따른 수익 또는 손실이 발생할 수 있어 주의가 필요하다."
  },
  {
    "term": "보증",
    "definition": "보증은(는) 자금이 필요한 개인이나 기업이 금융기관으로부터 자금을 빌리는 방식이다. 보증은 상환 능력과 금리에 따라 조건이 달라지며, 신용등급에 큰 영향을 미친다."
  },
  {
    "term": "자유적금",
    "definition": "자유적금은(는) 일정 기간 동안 자금을 은행에 맡기고 이자를 받는 저축 수단이다. 안정적인 자산 관리를 원하는 개인에게 적합하며, 금리와 만기 조건을 비교해 선택해야 한다."
  },
  {
    "term": "세액공제",
    "definition": "세액공제은(는) 국가나 지자체가 국민의 소득이나 소비에 부과하는 금전적 의무이다. 올바른 세액공제 처리를 위해 세법 지식과 정확한 회계 기준 준수가 필수적이다."
  },
  {
    "term": "적금",
    "definition": "적금은(는) 일정 기간 동안 자금을 은행에 맡기고 이자를 받는 저축 수단이다. 안정적인 자산 관리를 원하는 개인에게 적합하며, 금리와 만기 조건을 비교해 선택해야 한다."
  },
  {
    "term": "CFD",
    "definition": "CFD은(는) 기초 자산의 가치에 따라 수익이 결정되는 고위험 고수익 금융상품이다. CFD 투자는 높은 이해도와 시장 변동성에 대한 예측이 요구된다."
  },
  {
    "term": "소득세",
    "definition": "소득세은(는) 국가나 지자체가 국민의 소득이나 소비에 부과하는 금전적 의무이다. 올바른 소득세 처리를 위해 세법 지식과 정확한 회계 기준 준수가 필수적이다."
  },
  {
    "term": "채권",
    "definition": "채권은(는) 투자자들이 자산을 운용하고 수익을 창출하기 위해 사용하는 대표적인 금융 수단이다. 채권은 시장 흐름과 기업 가치 분석 등을 통해 전략적으로 접근하는 것이 중요하다."
  },
  {
    "term": "현금흐름",
    "definition": "현금흐름은(는) 재무 목표 달성을 위해 자산을 효율적으로 분배하고 운용하는 활동이다. 장기적인 현금흐름 설계는 노후 대비와 위험 분산에 핵심적인 역할을 한다."
  },
  {
    "term": "디지털지갑",
    "definition": "디지털지갑은(는) 정보기술을 기반으로 한 새로운 형태의 금융 서비스로, 빠른 거래와 편의성을 제공한다. 디지털지갑의 확산은 금융 접근성과 소비자 중심 서비스를 크게 향상시키고 있다."
  },
  {
    "term": "옵션",
    "definition": "옵션은(는) 기초 자산의 가치에 따라 수익이 결정되는 고위험 고수익 금융상품이다. 옵션 투자는 높은 이해도와 시장 변동성에 대한 예측이 요구된다."
  },
  {
    "term": "상환",
    "definition": "상환은(는) 자금이 필요한 개인이나 기업이 금융기관으로부터 자금을 빌리는 방식이다. 상환은 상환 능력과 금리에 따라 조건이 달라지며, 신용등급에 큰 영향을 미친다."
  },
  {
    "term": "연체이자",
    "definition": "연체이자은(는) 자금이 필요한 개인이나 기업이 금융기관으로부터 자금을 빌리는 방식이다. 연체이자은 상환 능력과 금리에 따라 조건이 달라지며, 신용등급에 큰 영향을 미친다."
  }
]
